gtfspy/__init__.py
gtfspy/calc_transfers.py
gtfspy/colormaps.py
gtfspy/exports.py
gtfspy/extended_route_types.py
gtfspy/filter.py
gtfspy/geometry.py
gtfspy/gtfs.py
gtfspy/import_gtfs.py
gtfspy/import_validator.py
gtfspy/mapviz.py
gtfspy/networks.py
gtfspy/osm_transfers.py
gtfspy/plots.py
gtfspy/route_types.py
gtfspy/segments.py
gtfspy/shapes.py
gtfspy/stats.py
gtfspy/timetable_validator.py
gtfspy/util.py
gtfspy/warnings_container.py
gtfspy/import_loaders/__init__.py
gtfspy/import_loaders/agency_loader.py
gtfspy/import_loaders/calendar_dates_loader.py
gtfspy/import_loaders/calendar_loader.py
gtfspy/import_loaders/day_loader.py
gtfspy/import_loaders/day_trips_materializer.py
gtfspy/import_loaders/feed_info_loader.py
gtfspy/import_loaders/frequencies_loader.py
gtfspy/import_loaders/metadata_loader.py
gtfspy/import_loaders/route_loader.py
gtfspy/import_loaders/shape_loader.py
gtfspy/import_loaders/stop_distances_loader.py
gtfspy/import_loaders/stop_loader.py
gtfspy/import_loaders/stop_times_loader.py
gtfspy/import_loaders/table_loader.py
gtfspy/import_loaders/transfer_loader.py
gtfspy/import_loaders/trip_loader.py
gtfspy/routing/__init__.py
gtfspy/routing/abstract_routing_algorithm.py
gtfspy/routing/connection.py
gtfspy/routing/connection_scan.py
gtfspy/routing/connection_scan_profile.py
gtfspy/routing/fastest_path_analyzer.py
gtfspy/routing/forwardjourney.py
gtfspy/routing/helpers.py
gtfspy/routing/journey_data.py
gtfspy/routing/journey_data_analyzer.py
gtfspy/routing/label.cpython-35m-darwin.so
gtfspy/routing/models.py
gtfspy/routing/multi_objective_pseudo_connection_scan_profiler.py
gtfspy/routing/node_profile_analyzer_time.py
gtfspy/routing/node_profile_analyzer_time_and_veh_legs.py
gtfspy/routing/node_profile_c.py
gtfspy/routing/node_profile_multiobjective.py
gtfspy/routing/node_profile_simple.py
gtfspy/routing/profile_block.py
gtfspy/routing/profile_block_analyzer.py
gtfspy-0.0.4.dist-info/DESCRIPTION.rst
gtfspy-0.0.4.dist-info/METADATA
gtfspy-0.0.4.dist-info/RECORD
gtfspy-0.0.4.dist-info/WHEEL
gtfspy-0.0.4.dist-info/metadata.json
gtfspy-0.0.4.dist-info/top_level.txt
