Metadata-Version: 2.0
Name: gtfspy
Version: 0.0.4
Summary: Python package for analyzing public transport timetables
Home-page: https://github.com/CxAalto/gtfspy
Author: Rainer Kujala
Author-email: Rainer.Kujala@gmail.com
License: MIT
Keywords: transit,routinggtfs,public transport,analysis,visualization
Platform: UNKNOWN
Classifier: Development Status :: 3 - Alpha
Classifier: Intended Audience :: Developers
Classifier: Intended Audience :: Science/Research
Classifier: Topic :: Scientific/Engineering :: GIS
Classifier: License :: OSI Approved :: MIT License
Classifier: Programming Language :: Python :: 3
Classifier: Programming Language :: Python :: 3.5
Requires-Dist: Cython
Requires-Dist: geoindex
Requires-Dist: geojson (==1.3.5)
Requires-Dist: matplotlib-scalebar (==0.3.1)
Requires-Dist: networkx (==1.11)
Requires-Dist: nose
Requires-Dist: osmread (==0.2)
Requires-Dist: pandas
Requires-Dist: pyproj
Requires-Dist: pyshp
Requires-Dist: setuptools (>=18.0)
Requires-Dist: shapely
Requires-Dist: six
Requires-Dist: smopy
